instruction_decoder.v
// -------------- Instruction Decoder ---------------- //

module instruction_decoder(
	input [7:0] opcode,
	output reg [6:0] ins_encode,
	output reg [2:0] source_reg, des_reg,
	output reg [1:0] reg_pair	
);

always@(*) begin
	casez(opcode)
		8'b00110110: begin // MVI M,data
			ins_encode = 7'd4;
			{source_reg,des_reg} = 6'd0;
			reg_pair = 2'b10;
		end
		8'b00111010: begin // LDA addr
			ins_encode = 7'd6;
			reg_pair = 2'b00; source_reg = 3'b000;
			des_reg = 3'b111;
		end
		8'b00110010: begin // STA addr
			ins_encode = 7'd7;
			reg_pair = 2'b00; des_reg = 3'b000;
			source_reg = 3'b111;
		end
		8'b00101010: begin // LHLD addr
			ins_encode = 7'd8;
			reg_pair = 2'b10;
			{des_reg, source_reg} = 6'd0;
		end
		8'b00100010: begin // SHLD addr
			ins_encode = 7'd9;
			reg_pair = 2'b10;
			{des_reg, source_reg} = 6'd0;
		end
		8'b11101001: begin // PCHL
			ins_encode = 7'd11;
			reg_pair = 2'b10;
			{des_reg, source_reg} = 6'd0;
		end
		8'b11110101: begin // PUSH PSW
			ins_encode = 7'd12;
			{des_reg, source_reg} = 6'd0;
			reg_pair = 2'b00;
		end
		8'b11101011: begin // XCHG
			ins_encode = 7'd16;
			reg_pair = 2'b01;
			{des_reg, source_reg} = 6'd0;
		end
		8'b10000110: begin // ADD M
			ins_encode = 7'd18;
			reg_pair = 2'b10;
			{des_reg, source_reg} = 6'd0;
		end
		8'b11000110: begin // ADI data
			ins_encode = 7'd19;
			reg_pair = 2'b00;
			{des_reg, source_reg} = 6'b111111;
		end
		8'b10001110: begin // ADC M
			ins_encode = 7'd21;
			reg_pair = 2'b10;
			{des_reg, source_reg} = 6'b111111;
		end
		8'b11001110: begin // ACI data
			ins_encode = 7'd22;
			reg_pair = 2'b00;
			{des_reg, source_reg} = 6'b111111;
		end
		8'b10010110: begin // SUB M
			ins_encode = 7'd24;
			reg_pair = 2'b10;
			{des_reg, source_reg} = 6'b111111;
		end
		8'b11010110: begin // SUI data
			ins_encode = 7'd25;
			reg_pair = 2'b00;
			{des_reg, source_reg} = 6'b111111;
		end
		8'b10011110: begin // SBB M
			ins_encode = 7'd27;
			reg_pair = 2'b10;
			{des_reg, source_reg} = 6'b111111;
		end
		8'b11011110: begin // SBI data
			ins_encode = 7'd28;
			reg_pair = 2'b00;
			{des_reg, source_reg} = 6'b111111;
		end
		8'b00110100: begin // INR M
			ins_encode = 7'd30;
			reg_pair = 2'b10;
			{des_reg, source_reg} = 6'd0;
		end
		8'b00110101: begin // DCR M
			ins_encode = 7'd32;
			reg_pair = 2'b10;
			{des_reg, source_reg} = 6'd0;
		end
		8'b00100111: begin // DAA
			ins_encode = 7'd36;
			reg_pair = 2'b00;
			{des_reg, source_reg} = 6'd0;
		end
		8'b10100110: begin // ANA M
			ins_encode = 7'd38;
			reg_pair = 2'b10;
			{des_reg, source_reg} = 6'b111111;
		end
		8'b11100110: begin // ANI data
			ins_encode = 7'd39;
			reg_pair = 2'b00;
			{source_reg,des_reg} = 6'b111111;
		end
		8'b10101110: begin // XRA M
			ins_encode = 7'd41;
			reg_pair = 2'b10;
			{des_reg, source_reg} = 6'b111111;
		end
		8'b11101110: begin // XRI data
			ins_encode = 7'd42;
			reg_pair = 2'b00;
			{des_reg, source_reg} = 6'b111111;
		end
		8'b10110110: begin // ORA M
			ins_encode = 7'd44;
			reg_pair = 2'b10;
			{source_reg,des_reg} = 6'b111111;
		end
		8'b11110110: begin // ORI data
			ins_encode = 7'd45;
			reg_pair = 2'b00;
			{source_reg,des_reg} = 6'b111111;
		end
        	8'b10111110: begin // CMP M
			ins_encode = 7'd47;
			reg_pair = 2'b10;
			{source_reg,des_reg} = 6'd0;
		end
		8'b11111110: begin // CPI data
			ins_encode = 7'd48;
			reg_pair = 2'b00;
			{source_reg,des_reg} = 6'b111000;
		end
		8'b00000111: begin // RLC
			ins_encode = 7'd49;
			reg_pair = 2'b00;
			{source_reg,des_reg} = 6'b111111;
		end
		8'b00001111: begin // RRC
			ins_encode = 7'd50;
			reg_pair = 2'b00;
			{source_reg,des_reg} = 6'b111111;
		end
		8'b00010111: begin // RAL
			ins_encode = 7'd51;
			reg_pair = 2'b00;
			{source_reg,des_reg} = 6'b111111;
		end
		8'b00011111: begin // RAR
			ins_encode = 7'd52;
			reg_pair = 2'b00;
			{source_reg,des_reg} = 6'b111111;
		end
		8'b00101111: begin // CMA
			ins_encode = 7'd53;
			reg_pair = 2'b00;
			{source_reg,des_reg} = 6'b111111;
		end
		8'b00111111: begin // CMC
			ins_encode = 7'd54;
			reg_pair = 2'b00;
			{source_reg,des_reg} = 6'd0;
		end
		8'b00110111: begin // STC
			ins_encode = 7'd55;
			reg_pair = 2'b00;
			{source_reg,des_reg} = 6'd0;
		end
		8'b11000011: begin // JMP addr
			ins_encode = 7'd56;
			reg_pair = 2'b00;
			{source_reg,des_reg} = 6'd0;
		end
        	8'b11001101: begin // CALL addr
            		ins_encode = 7'd57;
            		reg_pair = 2'b00;
            		{source_reg,des_reg} = 6'd0;
        	end
        	8'b11001001: begin // RET
            		ins_encode = 7'd60;
            		reg_pair = 2'b00;
            		{source_reg,des_reg} = 6'd0;            
        	end
        	8'b11110001: begin // POP PSW
            		ins_encode = 7'd63;
            		reg_pair = 2'b00;
            		{source_reg,des_reg} = 6'd0;             
        	end
        	8'b11100011: begin // XTHL
            		ins_encode = 7'd64;
            		reg_pair = 2'b10;
            		{source_reg,des_reg} = 6'd0;
        	end
        	8'b11111001: begin // SPHL
            		ins_encode = 7'd65;
            		reg_pair = 2'b10;
            		{source_reg,des_reg} = 6'd0;            
        	end
        	8'b11011011: begin // IN port
            		ins_encode = 7'd66;
            		reg_pair = 2'b00; source_reg = 3'b000;
            		des_reg = 3'b111;
        	end
        	8'b11010011: begin // OUT port
            		ins_encode = 7'd67;
            		reg_pair = 2'b00; des_reg = 3'b000;
            		source_reg = 3'b111;            
        	end
        	8'b11111011: begin // EI (Enable Interrupt)
            		ins_encode = 7'd68;
            		reg_pair = 2'b00;
            		{source_reg,des_reg} = 6'd0; 
        	end
        	8'b11110011: begin // DI (Disable Interrupt)
            		ins_encode = 7'd69;
            		reg_pair = 2'b00;
            		{source_reg,des_reg} = 6'd0; 
        	end
        	8'b01110110: begin // HLT
            		ins_encode = 7'd70;
            		reg_pair = 2'b00;
            		{source_reg,des_reg} = 6'd0; 
        	end
        	8'b00000000: begin // NOP (No Operation)
            		ins_encode = 7'd71;
            		reg_pair = 2'b00;
            		{source_reg,des_reg} = 6'd0; 
        	end
        	8'b00100000: begin // RIM
            		ins_encode = 7'd72;
            		reg_pair = 2'b00;
            		{source_reg,des_reg} = 6'd0; 
        	end
        	8'b00110000: begin // SIM
            		ins_encode = 7'd73;
            		reg_pair = 2'b00;
            		{source_reg,des_reg} = 6'd0;        
        	end

        	8'b00??0001: begin // LXI rp,data
			ins_encode = 7'd5;
			reg_pair = {opcode[5:4]};
			{source_reg,des_reg} = 6'b000;
		end
		8'b00??1010: begin // LDAX rp
			ins_encode = 7'd10;
			reg_pair = {opcode[5:4]};
			{des_reg, source_reg} = 6'd0;
		end
		8'b11??0101: begin // PUSH rp
			ins_encode = 7'd13;
			reg_pair = {opcode[5:4]};
			{des_reg, source_reg} = 6'd0;
		end
        	8'b11??0001: begin // POP rp
			ins_encode = 7'd14;
			reg_pair = {opcode[5:4]};
			{des_reg, source_reg} = 6'd0;
		end
		8'b00??0010: begin // STAX rp
			ins_encode = 7'd15;
			reg_pair = {opcode[5:4]};
			{des_reg, source_reg} = 6'd0;
		end
        	8'b00??0011: begin // INX rp
			ins_encode = 7'd33;
			reg_pair = {opcode[5:4]};
			{des_reg, source_reg} = 6'd0;
		end
		8'b00??1011: begin // DCX rp
			ins_encode = 7'd34;
			reg_pair = {opcode[5:4]};
			{des_reg, source_reg} = 6'd0;
		end
		8'b00??1001: begin // DAD rp
			ins_encode = 7'd35;
			reg_pair = {opcode[5:4]};
			{des_reg, source_reg} = 6'd0;
		end

        	8'b01110???: begin // MOV M,r
			ins_encode = 7'd2;
			source_reg = {opcode[2:0]}; des_reg = 3'b000;
			reg_pair = 2'b10;
		end
		8'b01???110: begin // MOV r,M
	        	ins_encode = 7'd1;
            		source_reg = 3'b000; des_reg = {opcode[5:3]};
            		reg_pair = 2'b10;
		end
        	8'b00???110: begin // MVI r,data
			ins_encode = 7'd3;
			source_reg = 3'b000; des_reg = {opcode[5:3]};
			reg_pair = 2'b00;
		end
        	8'b10000???: begin // ADD r
			ins_encode = 7'd17;
			reg_pair = 2'b00;
			source_reg = {opcode[2:0]}; des_reg = 3'b111;
		end
		8'b10001???: begin // ADC r
			ins_encode = 7'd20;
			reg_pair = 2'b00;
			source_reg = {opcode[2:0]}; des_reg = 3'b111;
		end
		8'b10010???: begin // SUB r
			ins_encode = 7'd23;
			reg_pair = 2'b00;
			source_reg = {opcode[2:0]}; des_reg = 3'b111;
		end
		8'b10011???: begin // SBB r
			ins_encode = 7'd26;
			reg_pair = 2'b00;
			des_reg = 3'b111; source_reg = {opcode[2:0]};
		end
		8'b00???100: begin // INR r
			ins_encode = 7'd29;
			reg_pair = 2'b00;
			source_reg = {opcode[5:3]}; des_reg = {opcode[5:3]};
		end
        		8'b00???101: begin // DCR r
			ins_encode = 7'd31;
			reg_pair = 2'b00;
			source_reg = {opcode[5:3]}; des_reg = {opcode[5:3]};
		end
		8'b10100???: begin // ANA r
			ins_encode = 7'd37;
			reg_pair = 2'b00;
			source_reg = {opcode[2:0]}; des_reg = 3'b111; 
		end
		8'b10101???: begin // XRA r
			ins_encode = 7'd40;
			reg_pair = 2'b00;
			source_reg = {opcode[2:0]}; des_reg = 3'b111;
		end
		8'b10110???: begin // ORA r
			ins_encode = 7'd43;
			reg_pair = 2'b00;
			source_reg = {opcode[2:0]}; des_reg = 3'b111;
		end
		8'b10111???: begin // CMP r
			ins_encode = 7'd46;
			reg_pair = 2'b00;
			source_reg = {opcode[2:0]}; des_reg = 3'b000;
		end
        	8'b11???010: begin // Jcondition addr
            		ins_encode = 7'd57;
            		reg_pair = 2'b00; des_reg = 3'b000;
            		source_reg = {opcode[5:3]}; // Using source register to store the condition
        	end
        	8'b11???100: begin // Ccondition addr
            		ins_encode = 7'd59;
            		reg_pair = 2'b00; des_reg = 3'b000;
            		source_reg = {opcode[5:3]}; // Using source register to store the condition
        	end
        	8'b11???000: begin // Rcondition
            		ins_encode = 7'd61;
            		reg_pair = 2'b00; des_reg = 3'b000;
            		source_reg = {opcode[5:3]}; // Using source register to store the condition
        	end
        	8'b11???111: begin // RST n
            		ins_encode = 7'd62;
            		reg_pair = 2'b00;
            		{source_reg,des_reg} = 6'd0;                
        	end

        	8'b01??????: begin // MOV r,r
            		ins_encode = 7'd0;
			source_reg = {opcode[2:0]}; des_reg = {opcode[5:3]};
            		reg_pair = 2'b00;
		end   

        	default: begin
            		ins_encode = 7'd127;
            		{source_reg,des_reg} = 6'd0;
            		reg_pair = 2'b00;
        	end

	endcase	
end

endmodule

instruction_decoder_tb.v
`timescale 1ns/1ps


module instruction_decoder_tb();

reg [7:0] opcode;
wire [6:0] ins_encode;
wire [2:0] source_reg, des_reg;
wire [1:0] reg_pair;

instruction_decoder dut(.opcode(opcode), .ins_encode(ins_encode), 
	.source_reg(source_reg), .des_reg(des_reg), .reg_pair(reg_pair));

initial begin
	$dumpfile("wav_instruction_decoder.vcd");
	$dumpvars(0,instruction_decoder_tb);
	$monitor("Time=%0t, opcode=%h, ins_encode=%d, source_reg=%b, des_reg=%b, reg_pair=%b",$time,opcode,ins_encode,source_reg,des_reg,reg_pair);

	opcode = 8'h76; #10;   // HLT
        opcode = 8'h80; #10;   // ADD B
        opcode = 8'h3E; #10;   // MVI A
        opcode = 8'h22; #10;   // SHLD
        opcode = 8'hD5; #10;   // PUSH DE
        opcode = 8'hC3; #10;   // JMP
        opcode = 8'h8E; #10;   // ADC M
        opcode = 8'h04; #10;   // INR B
        opcode = 8'hC9; #10;   // RET
        opcode = 8'h47; #10;   // MOV B,A
        opcode = 8'h36; #10;   // MVI M
        opcode = 8'hD6; #10;   // SUI
        opcode = 8'hF3; #10;   // DI
        opcode = 8'h19; #10;   // DAD DE
	opcode = 8'hA8; #10;   // XRA B
        opcode = 8'hEB; #10;   // XCHG
        opcode = 8'hCD; #10;   // CALL
        opcode = 8'hF6; #10;   // ORI
        opcode = 8'h2A; #10;   // LHLD
        opcode = 8'h32; #10;   // STA
        opcode = 8'hE9; #10;   // PCHL
        opcode = 8'hC6; #10;   // ADI
        opcode = 8'hDE; #10;   // SBI
        opcode = 8'hB8; #10;   // CMP B
        opcode = 8'h0B; #10;   // DCX BC
        opcode = 8'h2F; #10;   // CMA
        opcode = 8'h17; #10;   // RAL
        opcode = 8'h0F; #10;   // RRC
        opcode = 8'h07; #10;   // RLC
        opcode = 8'h1F; #10;   // RAR
        opcode = 8'h37; #10;   // STC
        opcode = 8'h3F; #10;   // CMC
        opcode = 8'h27; #10;   // DAA
	opcode = 8'hDB; #10;   // IN
        opcode = 8'hD3; #10;   // OUT
        opcode = 8'hFB; #10;   // EI
        opcode = 8'h20; #10;   // RIM
        opcode = 8'h30; #10;   // SIM
        opcode = 8'hF9; #10;   // SPHL
        opcode = 8'hE3; #10;   // XTHL
        opcode = 8'hF1; #10;   // POP PSW
        opcode = 8'hF5; #10;   // PUSH PSW
        opcode = 8'h0A; #10;   // LDAX BC
        opcode = 8'h12; #10;   // STAX DE
        opcode = 8'h01; #10;   // LXI BC
        opcode = 8'h23; #10;   // INX HL
        opcode = 8'h34; #10;   // INR M
        opcode = 8'h35; #10;   // DCR M
        opcode = 8'h86; #10;   // ADD M
        opcode = 8'h96; #10;   // SUB M
        opcode = 8'h9E; #10;   // SBB M
        opcode = 8'hA6; #10;   // ANA M
        opcode = 8'hAE; #10;   // XRA M
        opcode = 8'hB6; #10;   // ORA M
        opcode = 8'hBE; #10;   // CMP M
        opcode = 8'hCE; #10;   // ACI
        opcode = 8'hEE; #10;   // XRI
        opcode = 8'hE6; #10;   // ANI
        opcode = 8'hFE; #10;   // CPI
        opcode = 8'h88; #10;   // ADC B
        opcode = 8'h90; #10;   // SUB B
        opcode = 8'h98; #10;   // SBB B
        opcode = 8'hA0; #10;   // ANA B
        opcode = 8'hB0; #10;   // ORA B
        opcode = 8'h46; #10;   // MOV B,M
        opcode = 8'h70; #10;   // MOV M,B
        opcode = 8'hC2; #10;   // JNZ
        opcode = 8'hC4; #10;   // CNZ
        opcode = 8'hC0; #10;   // RNZ
        opcode = 8'hC7; #10;   // RST 0
        opcode = 8'h3A; #10;   // LDA
        opcode = 8'h00; #10;   // NOP

	// Invalid opcode
	opcode = 8'h08; #10;

	$display("All test cases completed");
	$finish;	
end

endmodule

wav_instruction_decoder.vcd
$date
	Sat Jul 11 11:12:24 2026
$end
$version
	Icarus Verilog
$end
$timescale
	1ps
$end
$scope module instruction_decoder_tb $end
$var wire 3 ! source_reg [2:0] $end
$var wire 2 " reg_pair [1:0] $end
$var wire 7 # ins_encode [6:0] $end
$var wire 3 $ des_reg [2:0] $end
$var reg 8 % opcode [7:0] $end
$scope module dut $end
$var wire 8 & opcode [7:0] $end
$var reg 3 ' des_reg [2:0] $end
$var reg 7 ( ins_encode [6:0] $end
$var reg 2 ) reg_pair [1:0] $end
$var reg 3 * source_reg [2:0] $end
$upscope $end
$upscope $end
$enddefinitions $end
$comment Show the parameter values. $end
$dumpall
$end
#0
$dumpvars
b0 *
b0 )
b1000110 (
b0 '
b1110110 &
b1110110 %
b0 $
b1000110 #
b0 "
b0 !
$end
#10000
b111 $
b111 '
b10001 #
b10001 (
b10000000 %
b10000000 &
#20000
b11 #
b11 (
b111110 %
b111110 &
#30000
b0 $
b0 '
b10 "
b10 )
b1001 #
b1001 (
b100010 %
b100010 &
#40000
b1 "
b1 )
b1101 #
b1101 (
b11010101 %
b11010101 &
#50000
b0 "
b0 )
b111000 #
b111000 (
b11000011 %
b11000011 &
#60000
b111 $
b111 '
b111 !
b111 *
b10 "
b10 )
b10101 #
b10101 (
b10001110 %
b10001110 &
#70000
b0 $
b0 '
b0 !
b0 *
b0 "
b0 )
b11101 #
b11101 (
b100 %
b100 &
#80000
b111100 #
b111100 (
b11001001 %
b11001001 &
#90000
b111 !
b111 *
b0 #
b0 (
b1000111 %
b1000111 &
#100000
b10 "
b10 )
b0 !
b0 *
b100 #
b100 (
b110110 %
b110110 &
#110000
b111 $
b111 '
b111 !
b111 *
b0 "
b0 )
b11001 #
b11001 (
b11010110 %
b11010110 &
#120000
b0 !
b0 *
b0 $
b0 '
b1000101 #
b1000101 (
b11110011 %
b11110011 &
#130000
b1 "
b1 )
b100011 #
b100011 (
b11001 %
b11001 &
#140000
b111 $
b111 '
b0 "
b0 )
b101000 #
b101000 (
b10101000 %
b10101000 &
#150000
b0 $
b0 '
b1 "
b1 )
b10000 #
b10000 (
b11101011 %
b11101011 &
#160000
b0 "
b0 )
b111001 #
b111001 (
b11001101 %
b11001101 &
#170000
b111 !
b111 *
b111 $
b111 '
b101101 #
b101101 (
b11110110 %
b11110110 &
#180000
b0 $
b0 '
b0 !
b0 *
b10 "
b10 )
b1000 #
b1000 (
b101010 %
b101010 &
#190000
b111 !
b111 *
b0 "
b0 )
b111 #
b111 (
b110010 %
b110010 &
#200000
b0 !
b0 *
b10 "
b10 )
b1011 #
b1011 (
b11101001 %
b11101001 &
#210000
b111 $
b111 '
b111 !
b111 *
b0 "
b0 )
b10011 #
b10011 (
b11000110 %
b11000110 &
#220000
b11100 #
b11100 (
b11011110 %
b11011110 &
#230000
b0 $
b0 '
b0 !
b0 *
b101110 #
b101110 (
b10111000 %
b10111000 &
#240000
b100010 #
b100010 (
b1011 %
b1011 &
#250000
b111 !
b111 *
b111 $
b111 '
b110101 #
b110101 (
b101111 %
b101111 &
#260000
b110011 #
b110011 (
b10111 %
b10111 &
#270000
b110010 #
b110010 (
b1111 %
b1111 &
#280000
b110001 #
b110001 (
b111 %
b111 &
#290000
b110100 #
b110100 (
b11111 %
b11111 &
#300000
b0 !
b0 *
b0 $
b0 '
b110111 #
b110111 (
b110111 %
b110111 &
#310000
b110110 #
b110110 (
b111111 %
b111111 &
#320000
b100100 #
b100100 (
b100111 %
b100111 &
#330000
b111 $
b111 '
b1000010 #
b1000010 (
b11011011 %
b11011011 &
#340000
b111 !
b111 *
b0 $
b0 '
b1000011 #
b1000011 (
b11010011 %
b11010011 &
#350000
b0 !
b0 *
b1000100 #
b1000100 (
b11111011 %
b11111011 &
#360000
b1001000 #
b1001000 (
b100000 %
b100000 &
#370000
b1001001 #
b1001001 (
b110000 %
b110000 &
#380000
b10 "
b10 )
b1000001 #
b1000001 (
b11111001 %
b11111001 &
#390000
b1000000 #
b1000000 (
b11100011 %
b11100011 &
#400000
b0 "
b0 )
b111111 #
b111111 (
b11110001 %
b11110001 &
#410000
b1100 #
b1100 (
b11110101 %
b11110101 &
#420000
b1010 #
b1010 (
b1010 %
b1010 &
#430000
b1 "
b1 )
b1111 #
b1111 (
b10010 %
b10010 &
#440000
b0 "
b0 )
b101 #
b101 (
b1 %
b1 &
#450000
b10 "
b10 )
b100001 #
b100001 (
b100011 %
b100011 &
#460000
b11110 #
b11110 (
b110100 %
b110100 &
#470000
b100000 #
b100000 (
b110101 %
b110101 &
#480000
b10010 #
b10010 (
b10000110 %
b10000110 &
#490000
b111 $
b111 '
b111 !
b111 *
b11000 #
b11000 (
b10010110 %
b10010110 &
#500000
b11011 #
b11011 (
b10011110 %
b10011110 &
#510000
b100110 #
b100110 (
b10100110 %
b10100110 &
#520000
b101001 #
b101001 (
b10101110 %
b10101110 &
#530000
b101100 #
b101100 (
b10110110 %
b10110110 &
#540000
b0 !
b0 *
b0 $
b0 '
b101111 #
b101111 (
b10111110 %
b10111110 &
#550000
b111 $
b111 '
b111 !
b111 *
b0 "
b0 )
b10110 #
b10110 (
b11001110 %
b11001110 &
#560000
b101010 #
b101010 (
b11101110 %
b11101110 &
#570000
b100111 #
b100111 (
b11100110 %
b11100110 &
#580000
b0 $
b0 '
b110000 #
b110000 (
b11111110 %
b11111110 &
#590000
b111 $
b111 '
b0 !
b0 *
b10100 #
b10100 (
b10001000 %
b10001000 &
#600000
b10111 #
b10111 (
b10010000 %
b10010000 &
#610000
b11010 #
b11010 (
b10011000 %
b10011000 &
#620000
b100101 #
b100101 (
b10100000 %
b10100000 &
#630000
b101011 #
b101011 (
b10110000 %
b10110000 &
#640000
b10 "
b10 )
b0 $
b0 '
b1 #
b1 (
b1000110 %
b1000110 &
#650000
b10 #
b10 (
b1110000 %
b1110000 &
#660000
b0 "
b0 )
b111001 #
b111001 (
b11000010 %
b11000010 &
#670000
b111011 #
b111011 (
b11000100 %
b11000100 &
#680000
b111101 #
b111101 (
b11000000 %
b11000000 &
#690000
b111110 #
b111110 (
b11000111 %
b11000111 &
#700000
b111 $
b111 '
b110 #
b110 (
b111010 %
b111010 &
#710000
b0 $
b0 '
b1000111 #
b1000111 (
b0 %
b0 &
#720000
b1111111 #
b1111111 (
b1000 %
b1000 &
